<exist xml:id="Ady_00588_0472">
    <teiHeader xmlns="http://www.tei-c.org/ns/1.0">
		<fileDesc>
			<titleStmt>
				<title type="main">SZEGÉNY, ÁRVA RIGÓIM</title>
				<author>
					<persName>
						<surname>Ady</surname>
						<forename>Endre</forename>
					</persName>
					<date from="1877" to="1919">1877-1919</date>
					<idno type="VIAF">56604836</idno>
				</author>
				<respStmt>
					<resp>ELTE Verskorpusz conversion</resp>
					<persName>
						<surname>Palkó</surname>
						<forename>Gábor</forename>
						<ref target="https://viaf.org/viaf/65989506"/>
					</persName>
					<persName>
						<surname>Horváth</surname>
						<forename>Péter</forename>
					</persName>
					<persName>
						<surname>Szlávich</surname>
						<forename>Eszter</forename>
					</persName>
					<persName>
						<surname>Indig</surname>
						<forename>Balázs</forename>
					</persName>
					<persName>
						<surname>Fellegi</surname>
						<forename>Zsófia</forename>
					</persName>
				</respStmt>
			</titleStmt>
			<extent>
				<measure unit="words">62</measure>
			</extent>
			<publicationStmt>
				<p>Published as part of ELTE Verskorpusz</p>
			</publicationStmt>
			<sourceDesc>
				<bibl>
					<title>SZEGÉNY, ÁRVA RIGÓIM</title>
					<author>
						<persName>
							<surname>Ady</surname>
							<forename>Endre</forename>
						</persName>
						<idno type="VIAF">56604836</idno>
					</author>
					<relatedItem type="copyText">
						<bibl>
							<title>Ady Endre összes költeményei</title>
							<date when="1997-11-17"/>
							<publisher>Magyar Elektronikus Könyvtárért Egyesület</publisher>
							<ref target="http://mek.oszk.hu/00500/00588"/>
							<respStmt>
								<resp>Original Electronic Edition</resp>
								<persName>
									<surname>Hevele</surname>
									<forename>István</forename>
								</persName>
								<persName>
									<surname>Szarka</surname>
									<forename>Gyula</forename>
								</persName>
								<persName>
									<surname>Pétery</surname>
									<forename>Kristóf</forename>
								</persName>
								<persName>
									<surname>Varga</surname>
									<forename>Mónika</forename>
								</persName>
								<persName>
									<surname>Kiss</surname>
									<forename>András</forename>
								</persName>
								<persName>
									<surname>Medgyesy</surname>
									<forename>Bence</forename>
									<forename>Attila</forename>
								</persName>
							</respStmt>
						</bibl>
					</relatedItem>
				</bibl>
			</sourceDesc>
		</fileDesc>
		<encodingDesc>
			<projectDesc>
				<p>ELTE Verskorpusz - automatic annotation</p>
			</projectDesc>
			<classDecl>
				<taxonomy xml:id="g">
					<category xml:id="g.p">
						<catDesc>poetry</catDesc>
						<category xml:id="g.pl">
							<catDesc>lyric poetry</catDesc>
						</category>
						<category xml:id="g.pn">
							<catDesc>narrative poetry</catDesc>
						</category>
					</category>
				</taxonomy>
			</classDecl>
		</encodingDesc>
		<profileDesc>
			<langUsage>
				<language ident="hu">Hungarian</language>
			</langUsage>
			<textClass>
				<catRef target="#g.p"/>
			</textClass>
		</profileDesc>
		<revisionDesc>
			<change when="2019-07-29">level1</change>
			<change when="2021-05-14">level2</change>
			<change when="2022-01-04">level3</change>
		</revisionDesc>
	</teiHeader>
    <text>
        <body>
            <div type="poem" div_numStanza="3" div_numLine="15" div_numWord="57" div_numSyll="126" div_numShortSyll="62" div_numLongSyll="64" div_rhyme="abcda|abcda|abcda" div_syllPattern="9-8-8-8-9|9-8-8-8-9|9-8-8-8-9">
                <head type="title">SZEGÉNY, ÁRVA RIGÓIM</head>
                <lg xml:id="lg1" lg_numLine="5" lg_numWord="17" lg_numSyll="42" lg_numShortSyll="21" lg_numLongSyll="21" rhyme="abcda" lg_syllPattern="9-8-8-8-9">
                    <l xml:id="l1" l_numWord="4" l_numSyll="9" l_numShortSyll="4" l_numLongSyll="5" real="110110010">
                        <w xml:id="w1" lemma="nóta" pos="NOUN" msd="Case=Nom|Number=Plur|Number[psor]=Sing|Person[psor]=1" w_numSyll="3" phonType="mixed" phonStruct="cBcBfc">Nótáim</w>
                        <pc xml:id="pc1" pos="PUNCT" join="left">,</pc>
                        <w xml:id="w2" lemma="én" pos="PRON" msd="Case=Nom|Number=Sing|Person=1|PronType=Prs" w_numSyll="1" phonType="high" phonStruct="Fc">én</w>
                        <w xml:id="w3" lemma="árva" pos="ADJ" msd="Case=Nom|Degree=Pos|Number=Sing" w_numSyll="2" phonType="low" phonStruct="Bccb">árva</w>
                        <w xml:id="w4" lemma="rigó" pos="NOUN" msd="Case=Nom|Number=Plur|Number[psor]=Sing|Person[psor]=1" w_numSyll="3" phonType="mixed" phonStruct="cfcBfc">rigóim</w>
                        <pc xml:id="pc2" pos="PUNCT" join="left">,</pc>
                    </l>
                    <l xml:id="l2" l_numWord="4" l_numSyll="8" l_numShortSyll="4" l_numLongSyll="4" real="10011100">
                        <w xml:id="w5" lemma="veszt" pos="VERB" msd="Definite=Ind|Mood=Imp|Number=Plur|Person=2|Tense=Pres|VerbForm=Fin|Voice=Act" w_numSyll="3" phonType="high" phonStruct="cfcccfcfc">Vesszetek</w>
                        <w xml:id="w6" lemma="el" pos="ADV" msd="_" w_numSyll="1" phonType="high" phonStruct="fc">el</w>
                        <pc xml:id="pc3" pos="PUNCT" join="left">:</pc>
                        <w xml:id="w7" lemma="nem" pos="ADV" msd="PronType=Neg" w_numSyll="1" phonType="high" phonStruct="cfc">nem</w>
                        <w xml:id="w8" lemma="tud" pos="VERB" msd="Definite=Ind|Mood=Ind|Number=Plur|Person=2|Tense=Past|VerbForm=Fin|Voice=Act" w_numSyll="3" phonType="low" phonStruct="cbccbcbc">tudtatok</w>
                    </l>
                    <l xml:id="l3" l_numWord="3" l_numSyll="8" l_numShortSyll="4" l_numLongSyll="4" real="11001100">
                        <w xml:id="w9" lemma="harsog" pos="VERB" msd="VerbForm=Inf|Voice=Act" w_numSyll="3" phonType="mixed" phonStruct="cbccbccf">Harsogni</w>
                        <w xml:id="w10" lemma="elég" pos="ADV" msd="_" w_numSyll="2" phonType="high" phonStruct="fcFc">elég</w>
                        <w xml:id="w11" lemma="gőgös" pos="ADJ" msd="Case=Ess|Degree=Pos|Number=Sing" w_numSyll="3" phonType="high" phonStruct="cFcfcfc">gőgösen</w>
                        <pc xml:id="pc4" pos="PUNCT" join="left">,</pc>
                    </l>
                    <l xml:id="l4" l_numWord="3" l_numSyll="8" l_numShortSyll="5" l_numLongSyll="3" real="01001100">
                        <w xml:id="w12" lemma="kacag" pos="VERB" msd="VerbForm=Inf|Voice=Act" w_numSyll="3" phonType="mixed" phonStruct="cbcbccf">Kacagni</w>
                        <w xml:id="w13" lemma="elég" pos="ADV" msd="_" w_numSyll="2" phonType="high" phonStruct="fcFc">elég</w>
                        <w xml:id="w14" lemma="boldog" pos="ADJ" msd="Case=Ess|Degree=Pos|Number=Sing" w_numSyll="3" phonType="low" phonStruct="cbccbcbc">boldogan</w>
                    </l>
                    <l xml:id="l5" l_numWord="3" l_numSyll="9" l_numShortSyll="4" l_numLongSyll="5" real="101101010">
                        <w xml:id="w15" lemma="hang" pos="NOUN" msd="Case=Nom|Number=Sing|Number[psor]=Plur|Person[psor]=2" w_numSyll="3" phonType="low" phonStruct="cbccbcbc">Hangotok</w>
                        <w xml:id="w16" lemma="bamba" pos="ADJ" msd="Case=Nom|Degree=Pos|Number=Sing" w_numSyll="2" phonType="low" phonStruct="cbccb">bamba</w>
                        <w xml:id="w17" lemma="hódoló" pos="NOUN" msd="Case=Sup|Number=Plur|Number[psor]=Sing|Person[psor]=3" w_numSyll="4" phonType="mixed" phonStruct="cBcbcBfc">hódolóin</w>
                        <pc xml:id="pc5" pos="PUNCT" join="left">.</pc>
                    </l>
                </lg>
                <lg xml:id="lg2" lg_numLine="5" lg_numWord="23" lg_numSyll="42" lg_numShortSyll="20" lg_numLongSyll="22" rhyme="abcda" lg_syllPattern="9-8-8-8-9">
                    <l xml:id="l6" l_numWord="5" l_numSyll="9" l_numShortSyll="3" l_numLongSyll="6" real="111101010">
                        <w xml:id="w18" lemma="hűvös" pos="ADJ" msd="Case=Nom|Degree=Pos|Number=Sing" w_numSyll="2" phonType="high" phonStruct="cFcfc">Hűvös</w>
                        <w xml:id="w19" lemma="van" pos="VERB" msd="Definite=Ind|Mood=Ind|Number=Sing|Person=3|Tense=Pres|VerbForm=Fin|Voice=Act" w_numSyll="1" phonType="low" phonStruct="cbc">van</w>
                        <w xml:id="w20" lemma="már" pos="ADV" msd="_" w_numSyll="1" phonType="low" phonStruct="cBc">már</w>
                        <w xml:id="w21" lemma="a" pos="DET" msd="Definite=Def|PronType=Art" w_numSyll="1" phonType="low" phonStruct="b">a</w>
                        <w xml:id="w22" lemma="kert" pos="NOUN" msd="Case=Ine|Number=Sing|Number[psor]=Plur|Person[psor]=2" w_numSyll="4" phonType="high" phonStruct="cfccfcfccfc">kertetekben</w>
                    </l>
                    <l xml:id="l7" l_numWord="4" l_numSyll="8" l_numShortSyll="6" l_numLongSyll="2" real="10000100">
                        <w xml:id="w23" lemma="s" pos="CONJ" msd="_" w_numSyll="0" phonType="noVowels" phonStruct="c">S</w>
                        <w xml:id="w24" lemma="rajtat" pos="NOUN" msd="Case=Nom|Number=Plur" w_numSyll="3" phonType="low" phonStruct="cbccbcbc">rajtatok</w>
                        <w xml:id="w25" lemma="a" pos="DET" msd="Definite=Def|PronType=Art" w_numSyll="1" phonType="low" phonStruct="b">a</w>
                        <w xml:id="w26" lemma="csirip-had" pos="NOUN" msd="Case=Nom|Number=Plur" w_numSyll="4" phonType="mixed" phonStruct="cfcfccbcbc">csirip-hadak</w>
                        <pc xml:id="pc6" pos="PUNCT" join="left">,</pc>
                    </l>
                    <l xml:id="l8" l_numWord="3" l_numSyll="8" l_numShortSyll="5" l_numLongSyll="3" real="10001100">
                        <w xml:id="w27" lemma="rajtat" pos="NOUN" msd="Case=Nom|Number=Plur" w_numSyll="3" phonType="low" phonStruct="cbccbcbc">Rajtatok</w>
                        <w xml:id="w28" lemma="az" pos="DET" msd="Definite=Def|PronType=Art" w_numSyll="1" phonType="low" phonStruct="bc">az</w>
                        <w xml:id="w29" lemma="ál-gőgös" pos="NOUN" msd="Case=Nom|Number=Plur" w_numSyll="4" phonType="mixed" phonStruct="BccFcfcfc">ál-gőgösök</w>
                    </l>
                    <l xml:id="l9" l_numWord="6" l_numSyll="8" l_numShortSyll="3" l_numLongSyll="5" real="01111100">
                        <w xml:id="w30" lemma="s" pos="CONJ" msd="_" w_numSyll="0" phonType="noVowels" phonStruct="c">S</w>
                        <w xml:id="w31" lemma="ti" pos="PRON" msd="Case=Nom|Number=Plur|Person=2|PronType=Prs" w_numSyll="1" phonType="high" phonStruct="cf">ti</w>
                        <w xml:id="w32" lemma="nem" pos="ADV" msd="PronType=Neg" w_numSyll="1" phonType="high" phonStruct="cfc">nem</w>
                        <w xml:id="w33" lemma="tud" pos="VERB" msd="Definite=Def|Mood=Ind|Number=Plur|Person=2|Tense=Pres|VerbForm=Fin|Voice=Act" w_numSyll="3" phonType="low" phonStruct="cbccBcbc">tudjátok</w>
                        <w xml:id="w34" lemma="meg" pos="PART" msd="_" w_numSyll="1" phonType="high" phonStruct="cfc">meg</w>
                        <w xml:id="w35" lemma="soha" pos="ADV" msd="_" w_numSyll="2" phonType="low" phonStruct="cbcb">soha</w>
                        <pc xml:id="pc7" pos="PUNCT" join="left">,</pc>
                    </l>
                    <l xml:id="l10" l_numWord="5" l_numSyll="9" l_numShortSyll="3" l_numLongSyll="6" real="111110010">
                        <w xml:id="w36" lemma="hogy" pos="PRON" msd="Case=Nom|Number=Sing|Person=3|PronType=Int" w_numSyll="1" phonType="low" phonStruct="cbc">Hogy</w>
                        <w xml:id="w37" lemma="nem" pos="ADV" msd="PronType=Neg" w_numSyll="1" phonType="high" phonStruct="cfc">nem</w>
                        <w xml:id="w38" lemma="nótázik" pos="VERB" msd="Definite=Ind|Mood=Ind|Number=Plur|Person=3|Tense=Past|VerbForm=Fin|Voice=Act" w_numSyll="3" phonType="low" phonStruct="cBcBccbc">nótáztak</w>
                        <w xml:id="w39" lemma="soha" pos="ADV" msd="_" w_numSyll="2" phonType="low" phonStruct="cbcb">soha</w>
                        <w xml:id="w40" lemma="szép" pos="ADJ" msd="Case=Ess|Degree=Cmp|Number=Sing" w_numSyll="2" phonType="high" phonStruct="cfccfc">szebben</w>
                        <pc xml:id="pc8" pos="PUNCT" join="left">.</pc>
                    </l>
                </lg>
                <lg xml:id="lg3" lg_numLine="5" lg_numWord="17" lg_numSyll="42" lg_numShortSyll="21" lg_numLongSyll="21" rhyme="abcda" lg_syllPattern="9-8-8-8-9">
                    <l xml:id="l11" l_numWord="4" l_numSyll="9" l_numShortSyll="4" l_numLongSyll="5" real="110110010">
                        <w xml:id="w41" lemma="nóta" pos="NOUN" msd="Case=Nom|Number=Plur|Number[psor]=Sing|Person[psor]=1" w_numSyll="3" phonType="mixed" phonStruct="cBcBfc">Nótáim</w>
                        <pc xml:id="pc9" pos="PUNCT" join="left">,</pc>
                        <w xml:id="w42" lemma="én" pos="PRON" msd="Case=Nom|Number=Sing|Person=1|PronType=Prs" w_numSyll="1" phonType="high" phonStruct="Fc">én</w>
                        <w xml:id="w43" lemma="árva" pos="ADJ" msd="Case=Nom|Degree=Pos|Number=Sing" w_numSyll="2" phonType="low" phonStruct="Bccb">árva</w>
                        <w xml:id="w44" lemma="rigó" pos="NOUN" msd="Case=Nom|Number=Plur|Number[psor]=Sing|Person[psor]=1" w_numSyll="3" phonType="mixed" phonStruct="cfcBfc">rigóim</w>
                        <pc xml:id="pc10" pos="PUNCT" join="left">,</pc>
                    </l>
                    <l xml:id="l12" l_numWord="4" l_numSyll="8" l_numShortSyll="4" l_numLongSyll="4" real="10011100">
                        <w xml:id="w45" lemma="veszt" pos="VERB" msd="Definite=Ind|Mood=Imp|Number=Plur|Person=2|Tense=Pres|VerbForm=Fin|Voice=Act" w_numSyll="3" phonType="high" phonStruct="cfcccfcfc">Vesszetek</w>
                        <w xml:id="w46" lemma="el" pos="ADV" msd="_" w_numSyll="1" phonType="high" phonStruct="fc">el</w>
                        <pc xml:id="pc11" pos="PUNCT" join="left">:</pc>
                        <w xml:id="w47" lemma="nem" pos="ADV" msd="PronType=Neg" w_numSyll="1" phonType="high" phonStruct="cfc">nem</w>
                        <w xml:id="w48" lemma="tud" pos="VERB" msd="Definite=Ind|Mood=Ind|Number=Plur|Person=2|Tense=Past|VerbForm=Fin|Voice=Act" w_numSyll="3" phonType="low" phonStruct="cbccbcbc">tudtatok</w>
                    </l>
                    <l xml:id="l13" l_numWord="3" l_numSyll="8" l_numShortSyll="4" l_numLongSyll="4" real="11001100">
                        <w xml:id="w49" lemma="harsog" pos="VERB" msd="VerbForm=Inf|Voice=Act" w_numSyll="3" phonType="mixed" phonStruct="cbccbccf">Harsogni</w>
                        <w xml:id="w50" lemma="elég" pos="ADV" msd="_" w_numSyll="2" phonType="high" phonStruct="fcFc">elég</w>
                        <w xml:id="w51" lemma="gőgös" pos="ADJ" msd="Case=Ess|Degree=Pos|Number=Sing" w_numSyll="3" phonType="high" phonStruct="cFcfcfc">gőgösen</w>
                        <pc xml:id="pc12" pos="PUNCT" join="left">,</pc>
                    </l>
                    <l xml:id="l14" l_numWord="3" l_numSyll="8" l_numShortSyll="5" l_numLongSyll="3" real="01001100">
                        <w xml:id="w52" lemma="kacag" pos="VERB" msd="VerbForm=Inf|Voice=Act" w_numSyll="3" phonType="mixed" phonStruct="cbcbccf">Kacagni</w>
                        <w xml:id="w53" lemma="elég" pos="ADV" msd="_" w_numSyll="2" phonType="high" phonStruct="fcFc">elég</w>
                        <w xml:id="w54" lemma="boldog" pos="ADJ" msd="Case=Ess|Degree=Pos|Number=Sing" w_numSyll="3" phonType="low" phonStruct="cbccbcbc">boldogan</w>
                    </l>
                    <l xml:id="l15" l_numWord="3" l_numSyll="9" l_numShortSyll="4" l_numLongSyll="5" real="101101010">
                        <w xml:id="w55" lemma="hang" pos="NOUN" msd="Case=Nom|Number=Sing|Number[psor]=Plur|Person[psor]=2" w_numSyll="3" phonType="low" phonStruct="cbccbcbc">Hangotok</w>
                        <w xml:id="w56" lemma="bamba" pos="ADJ" msd="Case=Nom|Degree=Pos|Number=Sing" w_numSyll="2" phonType="low" phonStruct="cbccb">bamba</w>
                        <w xml:id="w57" lemma="hódoló" pos="NOUN" msd="Case=Sup|Number=Plur|Number[psor]=Sing|Person[psor]=3" w_numSyll="4" phonType="mixed" phonStruct="cBcbcBfc">hódolóin</w>
                        <pc xml:id="pc13" pos="PUNCT" join="left">.</pc>
                    </l>
                </lg>
            </div>
            <rhymePairs>
                <rhymePair target="#w4 #w17">
                    <firstRhyme rhyme_lemma="rigó" rhyme_pos="NOUN" rhyme_msd="Case=Nom|Number=Plur|Number[psor]=Sing|Person[psor]=1" rhyme_numSyll="3" rhyme_phonType="mixed" rhyme_phonStruct="cfcBfc">rigóim</firstRhyme>
                    <secondRhyme rhyme_lemma="hódoló" rhyme_pos="NOUN" rhyme_msd="Case=Sup|Number=Plur|Number[psor]=Sing|Person[psor]=3" rhyme_numSyll="4" rhyme_phonType="mixed" rhyme_phonStruct="cBcbcBfc">hódolóin</secondRhyme>
                </rhymePair>
                <rhymePair target="#w22 #w40">
                    <firstRhyme rhyme_lemma="kert" rhyme_pos="NOUN" rhyme_msd="Case=Ine|Number=Sing|Number[psor]=Plur|Person[psor]=2" rhyme_numSyll="4" rhyme_phonType="high" rhyme_phonStruct="cfccfcfccfc">kertetekben</firstRhyme>
                    <secondRhyme rhyme_lemma="szép" rhyme_pos="ADJ" rhyme_msd="Case=Ess|Degree=Cmp|Number=Sing" rhyme_numSyll="2" rhyme_phonType="high" rhyme_phonStruct="cfccfc">szebben</secondRhyme>
                </rhymePair>
                <rhymePair target="#w44 #w57">
                    <firstRhyme rhyme_lemma="rigó" rhyme_pos="NOUN" rhyme_msd="Case=Nom|Number=Plur|Number[psor]=Sing|Person[psor]=1" rhyme_numSyll="3" rhyme_phonType="mixed" rhyme_phonStruct="cfcBfc">rigóim</firstRhyme>
                    <secondRhyme rhyme_lemma="hódoló" rhyme_pos="NOUN" rhyme_msd="Case=Sup|Number=Plur|Number[psor]=Sing|Person[psor]=3" rhyme_numSyll="4" rhyme_phonType="mixed" rhyme_phonStruct="cBcbcBfc">hódolóin</secondRhyme>
                </rhymePair>
            </rhymePairs>
            <alliterations>
                <alliteration target="#w14 #w15 #w16" allStruct="ana" posTags="ADJ NOUN ADJ" msdTags="Case=Ess|Degree=Pos|Number=Sing Case=Nom|Number=Sing|Number[psor]=Plur|Person[psor]=2 Case=Nom|Degree=Pos|Number=Sing" lemmas="boldog hang bamba">boldogan Hangotok bamba</alliteration>
                <alliteration target="#w15 #w16 #w17" allStruct="ana" posTags="NOUN ADJ NOUN" msdTags="Case=Nom|Number=Sing|Number[psor]=Plur|Person[psor]=2 Case=Nom|Degree=Pos|Number=Sing Case=Sup|Number=Plur|Number[psor]=Sing|Person[psor]=3" lemmas="hang bamba hódoló">Hangotok bamba hódolóin</alliteration>
                <alliteration target="#w31 #w32 #w33" allStruct="ana" posTags="PRON ADV VERB" msdTags="Case=Nom|Number=Plur|Person=2|PronType=Prs PronType=Neg Definite=Def|Mood=Ind|Number=Plur|Person=2|Tense=Pres|VerbForm=Fin|Voice=Act" lemmas="ti nem tud">ti nem tudjátok</alliteration>
                <alliteration target="#w37 #w38" allStruct="aa" posTags="ADV VERB" msdTags="PronType=Neg Definite=Ind|Mood=Ind|Number=Plur|Person=3|Tense=Past|VerbForm=Fin|Voice=Act" lemmas="nem nótázik">nem nótáztak</alliteration>
                <alliteration target="#w54 #w55 #w56" allStruct="ana" posTags="ADJ NOUN ADJ" msdTags="Case=Ess|Degree=Pos|Number=Sing Case=Nom|Number=Sing|Number[psor]=Plur|Person[psor]=2 Case=Nom|Degree=Pos|Number=Sing" lemmas="boldog hang bamba">boldogan Hangotok bamba</alliteration>
                <alliteration target="#w55 #w56 #w57" allStruct="ana" posTags="NOUN ADJ NOUN" msdTags="Case=Nom|Number=Sing|Number[psor]=Plur|Person[psor]=2 Case=Nom|Degree=Pos|Number=Sing Case=Sup|Number=Plur|Number[psor]=Sing|Person[psor]=3" lemmas="hang bamba hódoló">Hangotok bamba hódolóin</alliteration>
            </alliterations>
        </body>
    </text>
</exist>